filebackedarray/Hdf5CompressedSparseMatrixSeed.py
filebackedarray/Hdf5DenseArraySeed.py
filebackedarray/__init__.py
FileBackedArray-0.1.1.dist-info/LICENSE.txt
FileBackedArray-0.1.1.dist-info/METADATA
FileBackedArray-0.1.1.dist-info/WHEEL
FileBackedArray-0.1.1.dist-info/top_level.txt
FileBackedArray-0.1.1.dist-info/RECORD
