Metadata-Version: 2.1
Name: FileBackedArray
Version: 0.1.1
Summary: File backed objects for array and matrix like data
Home-page: https://github.com/biocpy/FileBackedArray
Author: Jayaram Kancherla
Author-email: jayaram.kancherla@gmail.com
License: MIT
Project-URL: Documentation, https://biocpy.github.io/FileBackedArray/
Platform: any
Classifier: Development Status :: 4 - Beta
Classifier: Programming Language :: Python
License-File: LICENSE.txt
Requires-Dist: delayedarray >=0.3.1
Requires-Dist: numpy
Requires-Dist: h5py
Requires-Dist: importlib-metadata ; python_version < "3.8"
Provides-Extra: testing
Requires-Dist: setuptools ; extra == 'testing'
Requires-Dist: pytest ; extra == 'testing'
Requires-Dist: pytest-cov ; extra == 'testing'
Requires-Dist: scipy ; extra == 'testing'
